rdnet/__init__.py
rdnet/rdnet.py
rdnet-0.1.2.dist-info/LICENSE
rdnet-0.1.2.dist-info/METADATA
rdnet-0.1.2.dist-info/NOTICE
rdnet-0.1.2.dist-info/WHEEL
rdnet-0.1.2.dist-info/top_level.txt
rdnet-0.1.2.dist-info/RECORD
