Metadata-Version: 2.1
Name: rdnet
Version: 0.1.2
Summary: RDNet (Densenets Reloaded: Paradigm shift beyond ResNets and ViTs)
Author-email: Donghyun Kim <dong.hyun@navercorp.om>
License: Apache License
Keywords: backbone,classification,densenet,convolutional-neural-networks,revisit,dense-connections,rdnet
Classifier: Programming Language :: Python :: 3
Requires-Python: >=3.8
License-File: LICENSE
License-File: NOTICE
Requires-Dist: torch >=1.9.1
Requires-Dist: timm ~=0.9
